odoo/addons/mail_private/README.rst
odoo/addons/mail_private/__init__.py
odoo/addons/mail_private/__manifest__.py
odoo/addons/mail_private/i18n/mail_private.pot
odoo/addons/mail_private/models/__init__.py
odoo/addons/mail_private/models/ir_attachment.py
odoo/addons/mail_private/models/ir_model.py
odoo/addons/mail_private/models/mail_channel.py
odoo/addons/mail_private/models/mail_message.py
odoo/addons/mail_private/models/mail_security_group.py
odoo/addons/mail_private/models/mail_thread.py
odoo/addons/mail_private/models/res_partner.py
odoo/addons/mail_private/models/res_users.py
odoo/addons/mail_private/readme/CONFIGURE.rst
odoo/addons/mail_private/readme/CONTRIBUTORS.rst
odoo/addons/mail_private/readme/DESCRIPTION.rst
odoo/addons/mail_private/readme/USAGE.rst
odoo/addons/mail_private/security/ir.model.access.csv
odoo/addons/mail_private/security/security.xml
odoo/addons/mail_private/static/description/icon.png
odoo/addons/mail_private/static/description/index.html
odoo/addons/mail_private/static/src/js/composer.js
odoo/addons/mail_private/static/src/js/message.js
odoo/addons/mail_private/static/src/less/message.less
odoo/addons/mail_private/static/src/xml/composer.xml
odoo/addons/mail_private/static/src/xml/thread.xml
odoo/addons/mail_private/tests/__init__.py
odoo/addons/mail_private/tests/test_mail_private.py
odoo/addons/mail_private/views/assets.xml
odoo/addons/mail_private/views/ir_model.xml
odoo/addons/mail_private/views/mail_message.xml
odoo/addons/mail_private/views/mail_security_group.xml
odoo/addons/mail_private/wizards/__init__.py
odoo/addons/mail_private/wizards/mail_compose_message.py
odoo/addons/mail_private/wizards/mail_compose_message.xml
odoo11_addon_mail_private-11.0.1.0.0.99.dev3.dist-info/METADATA
odoo11_addon_mail_private-11.0.1.0.0.99.dev3.dist-info/WHEEL
odoo11_addon_mail_private-11.0.1.0.0.99.dev3.dist-info/top_level.txt
odoo11_addon_mail_private-11.0.1.0.0.99.dev3.dist-info/RECORD
